tokenizador/__init__.py
tokenizador/tokenizador.py
spln_tokenizador-0.65.dist-info/entry_points.txt
spln_tokenizador-0.65.dist-info/LICENSE
spln_tokenizador-0.65.dist-info/WHEEL
spln_tokenizador-0.65.dist-info/METADATA
spln_tokenizador-0.65.dist-info/RECORD
