Metadata-Version: 2.1
Name: spln-tokenizador
Version: 0.65
Summary: Feito para a cadeira SPLN 2022/2023
Author-email: jpdiasfernandes <jpdiasfernandes13@gmail.com>
Classifier: License :: OSI Approved :: MIT License
Project-URL: Home, https://github.com/jpdiasfernandes/spln-2223
